<?xml version="1.0" encoding="UTF-8"?>
<?xml-model href="../../schema/dhqBiblio.rnc" type="application/relax-ng-compact-syntax?><?xml-model href="../../schema/dhqBiblio.sch" type="application/xml" schematypens="http://purl.oclc.org/dsdl/schematron"?><?xml-stylesheet type="text/css" href="../../css/dhqBiblio-formal.css" title="Formal" alternate="no"?><BiblioSet xmlns="http://digitalhumanities.org/dhq/ns/biblio">
   <WebSite ID="amazon" issuance="continuing">
      <author>
         <corporateName>Amazon</corporateName>
      </author>
      <title>Kindle, Wi-Fi, Graphite, 6" Display with New E Ink Pearl Technology</title>
      <url>http://www.amazon.com/Kindle-Wireless-Reader-Wifi-Graphite/dp/B002Y27P3M</url>
   </WebSite>
   <Book ID="barr2008" issuance="monographic">
      <author>
         <givenName>Pippin</givenName>
         <familyName>Barr</familyName>
      </author>
      <title>Crisis
            22</title>
      <place>Ottawa</place>
      <publisher>Hypertext and Hypermedia Lab</publisher>
      <date>2008</date>
      <note>Storytrek</note>
   </Book>
   <Book ID="benton2000" issuance="monographic">
      <author>
         <givenName>Megan L.</givenName>
         <familyName>Benton</familyName>
      </author>
      <title>Beauty
            and the Book: Fine Editions and Cultural Distinction in America</title>
      <place>New Haven</place>
      <publisher>Yale University Press</publisher>
      <date>2000</date>
   </Book>
   <WebSite ID="bernstein2003" issuance="continuing">
      <author>
         <givenName>Mark</givenName>
         <familyName>Bernstein</familyName>
      </author>
      <title>Patterns of Hypertext.</title>
      <publisher>Eastgate Systems</publisher>
      <url>http://www.eastgate.com/patterns/Patterns.html</url>
   </WebSite>
   <Book ID="bherer2009" issuance="monographic">
      <author>
         <givenName>Val</givenName>
         <familyName>Bherer</familyName>
      </author>
      <author>
         <givenName>Cindy</givenName>
         <familyName>Ma</familyName>
      </author>
      <author>
         <givenName>Elise</givenName>
         <familyName>Visit</familyName>
      </author>
      <title>Isolation U</title>
      <place>Ottawa</place>
      <publisher>Carleton University Hypertext and Hypermedia Lab</publisher>
      <date>2009</date>
      <note>Storytrek</note>
   </Book>
   <Book ID="bogost2007" issuance="monographic">
      <author>
         <givenName>Ian</givenName>
         <familyName>Bogost</familyName>
      </author>
      <title>Persuasive
            Games: The Expressive Power of Videogames</title>
      <place>Cambridge</place>
      <publisher>MIT Press</publisher>
      <date>2007 </date>
   </Book>
   <Book ID="boluk2011" issuance="monographic">
      <editor>
         <givenName>Stephanie</givenName>
         <familyName>Boluk</familyName>
      </editor>
      <editor>
         <givenName>Wylie</givenName>
         <familyName>Lenz</familyName>
      </editor>
      <title>Generation Zombie: Essays on the Living Dead in Modern
            Culture</title>
      <place>Jefferson</place>
      <publisher>McFarland Press</publisher>
      <date>2011</date>
   </Book>
   <JournalArticle ID="bull2005" issuance="monographic">
      <author>
         <givenName>Michael</givenName>
         <familyName>Bull</familyName>
      </author>
      <title>No Dead Air!
            The iPod and the Culture of Mobile Listening,</title>
      <journal issuance="continuing">
         <title>Leisure Studies</title>
         <volume>24</volume>
         <issue>4</issue>
         <date>2005</date>
      </journal>
      <startingPage>343</startingPage>
      <endingPage>355</endingPage>
   </JournalArticle>
   <JournalArticle ID="eaket2008" issuance="monographic">
      <author>
         <givenName>Chris</givenName>
         <familyName>Eaket</familyName>
      </author>
      <title>Project [murmur] and the Performativity of Space,</title>
      <journal issuance="continuing">
         <title>Theatre Research in Canada</title>
         <volume>29</volume>
         <issue>1</issue>
         <date>2008</date>
      </journal>
      <startingPage>29</startingPage>
      <endingPage>50</endingPage>
      <url>http://www.lib.unb.ca/Texts/TRIC/vol29 _1/tric29_1art02.pdf</url>
   </JournalArticle>
   <JournalArticle ID="emmott1998" issuance="monographic">
      <author>
         <givenName>Catherine</givenName>
         <familyName>Emmott</familyName>
      </author>
      <title>
         Situated Events in Fictional Worlds: The Reader's Role in
            Context Construction,</title>
      <journal issuance="continuing">
         <title>European Journal of English Studies</title>
         <volume>2</volume>
         <issue>2</issue>
         <date>1998</date>
      </journal>
      <startingPage>175</startingPage>
      <endingPage>194</endingPage>
   </JournalArticle>
   <JournalArticle ID="evans2010" issuance="monographic">
      <author>
         <givenName>Bob</givenName>
         <familyName>Evans</familyName>
      </author>
      <title>Steve Jobs
            Torpedoes Another Stale Model.</title>
      <journal issuance="continuing">
         <title>Information Week</title>
         <date>February 15 2010</date>
      </journal>
      <startingPage>8</startingPage>
      <endingPage>8</endingPage>
   </JournalArticle>
   <JournalArticle ID="galloway2010" issuance="monographic">
      <author>
         <givenName>Anne</givenName>
         <familyName>Galloway</familyName>
      </author>
      <title>Locating Media Futures in the Present; Or How to map Emergent Associations &amp;
            Expectations,</title>
      <journal issuance="continuing">
         <title>Aether: The Journal of Media
            Geography</title>
         <issue>5A</issue>
         <date>2010</date>
      </journal>
      <startingPage>27</startingPage>
      <endingPage>36</endingPage>
   </JournalArticle>
   <Book ID="gerrig1993" issuance="monographic">
      <author>
         <givenName>Richard J.</givenName>
         <familyName>Gerrig</familyName>
      </author>
      <title>Experiencing Narrative Worlds: On the Psychological Activities of Reading</title>
      <place>New Haven</place>
      <publisher>Yale University Press</publisher>
      <date>1993</date>
   </Book>
   <ConferencePaper ID="giles2009" issuance="monographic">
      <author>
         <givenName>Thierry</givenName>
         <familyName>Giles</familyName>
      </author>
      <author>
         <givenName>Michael</givenName>
         <familyName>Marianek</familyName>
      </author>
      <author>
         <givenName>Sarah K.</givenName>
         <familyName>Freidel</familyName>
      </author>
      <title>URBAN ENCOUNTER: Location-Based Collective
            Storytelling,</title>
      <conference>
         <name>MobileHCI'09 (Bonn, Germany)</name>
         <date>September 15-18 2009</date>
         <sponsor></sponsor>
      </conference>
   </ConferencePaper>
   <JournalArticle ID="green2004" issuance="monographic">
      <author>
         <givenName>Melanie C.</givenName>
         <familyName>Green</familyName>
      </author>
      <title>Transportation Into Narrative Worlds: The Role of Prior Knowledge and Perceived
            Realism,</title>
      <journal issuance="continuing">
         <title>Discourse Processes</title>
         <volume>38</volume>
         <issue>2</issue>
         <date>2004</date>
      </journal>
      <startingPage>247</startingPage>
      <endingPage>266</endingPage>
   </JournalArticle>
   <JournalArticle ID="greenetal2004" issuance="monographic">
      <author>
         <givenName>Melanie C.</givenName>
         <familyName>Green</familyName>
      </author>
      <author>
         <givenName>Timothy C.</givenName>
         <familyName>Brock</familyName>
      </author>
      <author>
         <givenName>Geoff F.</givenName>
         <familyName>Kaufmann</familyName>
      </author>
      <title>Understanding Media Enjoyment: The Role of
            Transportation into Narrative Worlds,</title>
      <journal issuance="continuing">
         <title>Communication Theory</title>
         <volume>14</volume>
         <issue>4</issue>
         <date>2004</date>
      </journal>
      <startingPage>311</startingPage>
      <endingPage>327</endingPage>
   </JournalArticle>
   <BookSection ID="greenspan2011">
      <author>
         <givenName>Brian</givenName>
         <familyName>Greenspan</familyName>
      </author>
      <title>A Brain is a
            Terrible Thing to Waste: Isolation U. and the Campus Zombie</title>
      <book issuance="monographic">
         <editor>
            <givenName>Stephanie</givenName>
            <familyName>Boluk</familyName>
         </editor>
         <editor>
            <givenName>Wylie</givenName>
            <familyName>Lenz</familyName>
         </editor>
         <title>Generation Zombie: Essays on the Living Dead in Modern
            Culture</title>
         <place>Jefferson</place>
         <publisher>McFarland Press</publisher>
         <date>2011</date>
      </book>
   </BookSection>
   <Book ID="harvey2000" issuance="monographic">
      <author>
         <givenName>David</givenName>
         <familyName>Harvey</familyName>
      </author>
      <title>Spaces of
            Hope</title>
      <place>Berkeley</place>
      <publisher>University of California Press</publisher>
      <date>2000</date>
   </Book>
   <Book ID="hayles2005" issuance="monographic">
      <author>
         <givenName>Katherine N.</givenName>
         <familyName>Hayles</familyName>
      </author>
      <title>My
            Mother Was a Computer: Digital Subjects and Literary Texts</title>
      <place>Chicago</place>
      <publisher>University of Chicago Press</publisher>
      <date>2005</date>
   </Book>
   <BookSection ID="hight2010">
      <author>
         <givenName>Jeremy</givenName>
         <familyName>Hight</familyName>
      </author>
      <title>Locative
            Narrative, Literature and Form,</title>
      <book issuance="monographic">
         <editor>
            <givenName>Jörgen</givenName>
            <familyName>Schäfer</familyName>
         </editor>
         <editor>
            <givenName>Peter</givenName>
            <familyName>Gendolla</familyName>
         </editor>
         <title>Beyond the Screen: Transformations of Literary Structures, Interfaces and Genres</title>
      </book>
      <startingPage>317</startingPage>
      <endingPage>330</endingPage>
   </BookSection>
   <Book ID="khaled2010" issuance="monographic">
      <author>
         <givenName>Rilla</givenName>
         <familyName>Khaled</familyName>
      </author>
     <author>
        <givenName>Pippin</givenName>
        <familyName>Barr</familyName>
     </author>
      <title>Salaam Copenhagen</title>
      <place>Storytrek, Copenhagen</place>
      <publisher>IT Copenhagen</publisher>
      <date>2010</date>
   </Book>
   <WebSite ID="klima2006" issuance="continuing">
      <author>
         <givenName>John</givenName>
         <familyName>Klima</familyName>
      </author>
      <title>Saint
            Joe.</title>
      <date>2006</date>
      <url>http://2006.01sj.org/ content/view/53/49</url>
      <note>Locative installation for the 13th Annual International Symposium of Electronic Art</note>
   </WebSite>
   <WebSite ID="knowltona" issuance="continuing">
      <author>
         <givenName>Jeff</givenName>
         <familyName>Knowlton</familyName>
      </author>
      <author>
         <givenName>Naomi</givenName>
         <familyName>Spellman</familyName>
      </author>
      <author>
         <givenName>Jeremy</givenName>
         <familyName>Hight</familyName>
      </author>
      <title>34 North 188 West: Mining the Urban Landscape</title>
      <url>http://www.34n118w.net/34N</url>
   </WebSite>
   <WebSite ID="knowltonb" issuance="continuing">
      <author>
         <givenName>Jeff</givenName>
         <familyName>Knowlton</familyName>
      </author>
      <author>
         <givenName>Naomi</givenName>
         <familyName>Spellman</familyName>
      </author>
      <author>
         <givenName>Brandon</givenName>
         <familyName>Stow</familyName>
      </author>
      <title>The Interpretive Engine for Various Places on Earth</title>
      <url>http://engine.34n118w.net</url>
   </WebSite>
   <ConferencePaper ID="lovlie2009" issuance="monographic">
      <author>
         <givenName>Anders Sundnes</givenName>
         <familyName>Løvlie</familyName>
      </author>
      <title>Poetic Augmented Reality: Place-bound Literature in Locative Media</title>
      <conference>
         <name>The 13th International MindTrek Conference: Everyday Life in the Ubiquitous Era, Tampere, Finland</name>
         <date>2009</date>
      </conference>
   </ConferencePaper>
   <Book ID="marin1984" issuance="monographic">
      <author>
         <givenName>Louis</givenName>
         <familyName>Marin</familyName>
      </author>
      <translator>
         <givenName>Robert A.</givenName>
         <familyName>Vollrath</familyName>
      </translator>
      <title>Utopics: The
            Semiological Play of Textual Spaces</title>
      <place>New York</place>
      <publisher>Humanity Books</publisher>
      <date>1984</date>
   </Book>
   <JournalArticle ID="miall2001" issuance="monographic">
      <author>
         <givenName>David S.</givenName>
         <familyName>Miall</familyName>
      </author>
      <author>
         <givenName>Teres</givenName>
         <familyName>Dobson</familyName>
      </author>
      <title>Reading Hypertext and the Experience of Literature,</title>
      <journal issuance="continuing">
         <title>Journal of Digital Information</title>
         <volume>2</volume>
         <issue>1</issue>
         <date>2001</date>
      </journal>
      <url>http://journals.tdl.org/jodi/article/viewArticle/35</url>
   </JournalArticle>
   <Artwork ID="micallef2003">
      <creator>
         <givenName>Shawn</givenName>
         <familyName>Micallef</familyName>
      </creator>
      <creator>
         <givenName>Gabe</givenName>
         <familyName>Sawhney</familyName>
      </creator>
      <creator>
         <givenName>James</givenName>
         <familyName>Roussel</familyName>
      </creator>
      <title>[murmur].</title>
      <place>Toronto</place>
      <note>Locative installation</note>
      <note>http://murmurtoronto.ca/about.php</note>
   </Artwork>
   <Book ID="mitchell1996" issuance="monographic">
      <author>
         <givenName>William J.</givenName>
         <familyName>Mitchell</familyName>
      </author>
      <title>City of Bits: Space, Place, and the Infobahn</title>
      <place>Cambridge</place>
      <publisher>MIT Press</publisher>
      <date>1996</date>
   </Book>
   <JournalArticle ID="philips2007" issuance="monographic">
      <author>
         <givenName>Deborah</givenName>
         <familyName>Philips</familyName>
      </author>
      <title>Talking Books: The Encounter of LIterature and Technology in the Audio Book,</title>
      <journal issuance="continuing">
         <title>Convergence</title>
         <volume>13</volume>
         <issue>3</issue>
         <date>2007</date>
      </journal>
      <startingPage>293</startingPage>
      <endingPage>306</endingPage>
   </JournalArticle>
   <JournalArticle ID="pope2006" issuance="monographic">
      <author>
         <givenName>James</givenName>
         <familyName>Pope</familyName>
      </author>
      <title>A Future for Hypertext
            Fiction,</title>
      <journal issuance="continuing">
         <title>Convergence</title>
         <volume>12</volume>
         <issue>4</issue>
         <date>2006</date>
      </journal>
      <startingPage>447</startingPage>
      <endingPage>465</endingPage>
   </JournalArticle>
   <BlogEntry ID="pressman2007" issuance="continuing">
      <author>
         <givenName>Aaron</givenName>
         <familyName>Pressman</familyName>
      </author>
      <title>Buy
            Amazon – Kindle is the iPod of Books.</title>
         <additionalTitle>Bloomberg Businessweek</additionalTitle>
         <date>2007</date>
      <url>http://www.businessweek.com/ investing/insights/blog/archives/2007/11/buy_amazon_-_kindle_is_the_ipod_of_ books.html</url>
   </BlogEntry>
   <WebSite ID="proboscis" issuance="continuing">
      <author>
         <corporateName>Proboscis</corporateName>
      </author>
      <title>Urban Tapestries</title>
      <url>http://proboscis.org.uk/projects/urban-tapestries</url>
   </WebSite>
   <BookSection ID="raley2010">
      <author>
         <givenName>Rita</givenName>
         <familyName>Raley</familyName>
      </author>
      <title>Walk This Way:
            Mobile Narrative as Composed Experience</title>
      <book issuance="monographic">
         <editor>
            <givenName>Jörgen</givenName>
            <familyName>Schäfer</familyName>
         </editor>
         <editor>
            <givenName>Peter</givenName>
            <familyName>Gendolla</familyName>
         </editor>
         <title>Beyond the Screen: Transformations of Literary Structures, Interfaces and Genres</title>
      </book>
      <startingPage>299</startingPage>
      <endingPage>316</endingPage>
   </BookSection>
   <BookSection ID="rober2006">
      <author>
         <givenName>Niklas</givenName>
         <familyName>Röber</familyName>
      </author>
      <author>
         <givenName>Cornelius</givenName>
         <familyName>Huber</familyName>
      </author>
      <author>
         <givenName>Knut</givenName>
         <familyName>Hartmann</familyName>
      </author>
      <author>
         <givenName>Matthias</givenName>
         <familyName>Feustel</familyName>
      </author>
      <author>
         <givenName>Maic</givenName>
         <familyName>Masuch</familyName>
      </author>
      <title>Interactive Audiobooks:
            Combining Narratives with Game Elements,</title>
      <book issuance="monographic">
         <title>Technologies
            for Interactive Digital Storytelling and Entertainment</title>
         <place>Berlin</place>
         <publisher>Springer</publisher>
         <date>2006</date>
      </book>
      <startingPage>358</startingPage>
      <endingPage>369</endingPage>
   </BookSection>
   <JournalArticle ID="rothbauer2009" issuance="monographic">
      <author>
         <givenName>Pauline</givenName>
         <familyName>Rothbauer</familyName>
      </author>
      <title>Exploring the Placelessness of Reading Among Older Teens in a Canadian Rural
            Municipality,</title>
      <journal issuance="continuing">
         <title>Library Quarterly</title>
         <volume>79</volume>
         <issue>4</issue>
         <date>2009</date>
      </journal>
      <startingPage>465</startingPage>
      <endingPage>483</endingPage>
 </JournalArticle>
   <Artwork ID="rueb2005">
      <creator>
         <givenName>Teri</givenName>
         <familyName>Rueb</familyName>
      </creator>
      <title>itinerant</title>
      <place>Boston</place>
      <date>2005</date>
      <url>http://www. turbulence.org/Works/itinerant</url>
      <note>Locative installation</note>
   </Artwork>
   <Artwork ID="rueb1996">
      <creator>
         <givenName>Teri</givenName>
         <familyName>Rueb</familyName>
      </creator>
      <title>TRACE: a memorial
            environmental sound installation</title>
      <place>Yoho National Park, British Columbia</place>
      <date>1996</date>
      <url>http://www. terirueb.net/trace/index.html</url>
      <note>Locative installation</note>
   </Artwork>
   <JournalArticle ID="ryan2004" issuance="monographic">
      <author>
         <givenName>Marie-Laure</givenName>
         <familyName>Ryan</familyName>
      </author>
      <title>Cyberspace, Cybertexts, Cybermaps,</title>
      <journal issuance="continuing">
         <title>Dichtung Digital</title>
         <date>2004</date>
      </journal>
      <url>http://www.brown.edu/Research/dichtung-digital/2004/1-Ryan.htm</url>
   </JournalArticle>
   <JournalArticle ID="ryan1980" issuance="monographic">
      <author>
         <givenName>Marie-Laure</givenName>
         <familyName>Ryan</familyName>
      </author>
      <title>Fiction,
            Non-Factuals, and the Principle of Minimal Departure,</title>
      <journal issuance="continuing">
         <title>Poetics</title>
         <volume>9</volume>
         <date>1980</date>
      </journal>
      <startingPage>403</startingPage>
      <endingPage>422</endingPage>
   </JournalArticle>
   <Book ID="schafer2010" issuance="monographic">
      <editor>
         <givenName>Jörgen</givenName>
         <familyName>Schäfer</familyName>
      </editor>
      <editor>
         <givenName>Peter</givenName>
         <familyName>Gendolla</familyName>
      </editor>
      <title>Beyond the Screen: Transformations of Literary
            Structures, Interfaces and Genres</title>
      <place>New Brunswick</place>
      <publisher>Transaction Publishers</publisher>
      <date>2010</date>
   </Book>
   <Artwork ID="spellman2004">
      <creator>
         <givenName>Naomi</givenName>
         <familyName>Spellman</familyName>
      </creator>
      <creator>
         <givenName>Jeff</givenName>
         <familyName>Knowlton</familyName>
      </creator>
      <title>InterUrban</title>
      <date>2004</date>
      <note>Locative installation for Mobile Connections, Futuresonic, Manchester, UK</note>
      <url>http://interurban.34n118w.net</url>
   </Artwork>
   <ConferencePaper ID="whitson2008" issuance="monographic">
      <author>
         <givenName>Jennifer</givenName>
         <familyName>Whitson</familyName>
      </author>
      <author>
         <givenName>Chris</givenName>
         <familyName>Eaket</familyName>
      </author>
      <author>
         <givenName>Brian</givenName>
         <familyName>Greenspan</familyName>
      </author>
      <author>
         <givenName>Minh Quang</givenName>
         <familyName>Tran</familyName>
      </author>
      <author>
         <givenName>Natalie</givenName>
         <familyName>King</familyName>
      </author>
      <title>Neo-Immersion: Awareness
            and Engagement in Gameplay,</title>
      <conference>
         <name>The 2008
            Conference on Future Play: Research, Play, Share</name>
         <date>2008</date>
         <sponsor></sponsor>
      </conference>
      <startingPage>220</startingPage>
      <endingPage>223</endingPage>
      <url>http://doi.acm.org/10.1145/1496984.1497028</url>
   </ConferencePaper>
</BiblioSet>