<?xml version="1.0" encoding="UTF-8"?>
<?xml-model href="../../schema/dhqBiblio.rnc" type="application/relax-ng-compact-syntax"?>
<?xml-model href="../../schema/dhqBiblio.sch" type="application/xml" schematypens="http://purl.oclc.org/dsdl/schematron"?>
<?xml-stylesheet type="text/css" href="../../css/dhqBiblio-formal.css" title="Formal" alternate="no"?>
<BiblioSet xmlns="http://digitalhumanities.org/dhq/ns/biblio">
   <ConferencePaper ID="tablan2002" issuance="monographic">
      <author>
         <givenName>Valentin</givenName>
         <familyName>Tablan</familyName>
      </author>
      <author>
         <givenName>Cristian</givenName>
         <familyName>Ursu</familyName>
      </author>
      <author>
         <givenName>Kalina</givenName>
         <familyName>Bontcheva</familyName>
      </author>
      <author>
         <givenName>Hamish</givenName>
         <familyName>Cunningham</familyName>
      </author>
      <author>
         <givenName>Diana</givenName>
         <familyName>Maynard</familyName>
      </author>
      <author>
         <givenName>Oana</givenName>
         <familyName>Hamza</familyName>
      </author>
      <author>
         <givenName>Mark</givenName>
         <familyName>Leisher</familyName>
      </author>
      <title>A Unicode-based Environment for Creation and Use of Language Resources</title>
      <conference>
         <name>3rd International Conference on Language Resources and Evaluation</name>
      </conference>
      <publication issuance="continuing">
         <title>Proceedings of the 3rd International Conference on Language Resources and Evaluation
        (LREC 2002)</title>
         <date>2002</date>
      </publication>
   </ConferencePaper>
   <JournalArticle ID="tagliamonte2005" issuance="monographic">
      <author>
         <givenName>Sali</givenName>
         <familyName>Tagliamonte</familyName>
      </author>
      <title>So who? Like how? Just what?: Discourse markers in the conversations of Young
      Canadians</title>
      <journal issuance="continuing">
         <title>Journal of Pragmatics</title>
         <volume>37</volume>
         <issue>11</issue>
         <date>2005</date>
      </journal>
      <startingPage>1896</startingPage>
      <endingPage>1915</endingPage>
   </JournalArticle>
   <ConferencePaper ID="takahashi2002" issuance="monographic">
      <author>
         <givenName>Toshiyuki</givenName>
         <familyName>Takahashi</familyName>
      </author>
      <author>
         <givenName>Hong</givenName>
         <familyName>Soonsang</familyName>
      </author>
      <author>
         <givenName>Kenjiro</givenName>
         <familyName>Taura</familyName>
      </author>
      <author>
         <givenName>Akinori</givenName>
         <familyName>Yonezawa</familyName>
      </author>
      <title>World Wide Web Crawler</title>
      <conference>
         <name>11th International World Wide Web Conference</name>
      </conference>
      <publication issuance="continuing">
         <title>Poster proceedings of the 11th International World Wide Web Conference</title>
         <date>2002</date>
      </publication>
   </ConferencePaper>
   <JournalArticle ID="takeuchi2006" issuance="monographic">
      <author>
         <givenName>Koichi</givenName>
         <familyName>Takeuchi</familyName>
      </author>
      <author>
         <givenName>Kentaro</givenName>
         <familyName>Inui</familyName>
      </author>
      <author>
         <givenName>Atsushi</givenName>
         <familyName>Fujita</familyName>
      </author>
      <title>Description of syntactic and semantic characteristics of Japanese verbs based on lexical
      conceptual structure</title>
      <journal issuance="continuing">
         <title>Lexicon Forum</title>
         <volume>2</volume>
         <date>2006</date>
      </journal>
      <startingPage>85</startingPage>
      <endingPage>120</endingPage>
   </JournalArticle>
   <JournalArticle ID="talbert1992" issuance="monographic">
      <author>
         <givenName>R.</givenName>
         <familyName>Talbert</familyName>
      </author>
      <title>Mapping the classical world: major atlases and map series 1872-1990</title>
      <journal issuance="continuing">
         <title>Journal of Roman Archaeology</title>
         <volume>5</volume>
         <date>1992</date>
      </journal>
      <startingPage>5</startingPage>
      <endingPage>38</endingPage>
   </JournalArticle>
   <ConferencePaper ID="tanaka1996" issuance="monographic">
      <author>
         <givenName>Kumiko</givenName>
         <familyName>Tanaka</familyName>
      </author>
      <author>
         <givenName>Hideya</givenName>
         <familyName>Iwasaki</familyName>
      </author>
      <title>Extraction of lexical translations from non-aligned corpora</title>
      <conference>
         <name>COLING 1996: 16th International Conference on Computational Linguistics</name>
      </conference>
      <publication issuance="continuing">
         <title>Proceedings of the 16th International Conference on Computational linguistics</title>
         <date>1996</date>
      </publication>
      <startingPage>580</startingPage>
      <endingPage>585</endingPage>
   </ConferencePaper>
   <JournalArticle ID="tanaka1998" issuance="monographic">
      <author>
         <givenName>Kumiji</givenName>
         <familyName>Tanaka</familyName>
      </author>
      <author>
         <givenName>Kyoji</givenName>
         <familyName>Umemura</familyName>
      </author>
      <author>
         <givenName>H.</givenName>
         <familyName>Iwasaki</familyName>
      </author>
      <title>Construction of a bilingual dictionary intermediated by a third language</title>
      <journal issuance="continuing">
         <title>Transactions of the Information Processing Society of Japan</title>
         <volume>39</volume>
         <issue>6</issue>
         <date>1998</date>
      </journal>
      <startingPage>1915</startingPage>
      <endingPage>1924</endingPage>
   </JournalArticle>
   <ConferencePaper ID="tanaka2005" issuance="monographic">
      <author>
         <givenName>T.</givenName>
         <familyName>Tanaka</familyName>
      </author>
      <etal/>
      <title>High precision treebanking – Blazing useful trees using POS information</title>
      <conference>
         <name>ACL-2005</name>
      </conference>
      <publication issuance="continuing">
         <date>2005</date>
      </publication>
      <startingPage>330</startingPage>
      <endingPage>337</endingPage>
   </ConferencePaper>
   <ConferencePaper ID="tanaka2006" issuance="monographic">
      <author>
         <givenName>T.</givenName>
         <familyName>Tanaka</familyName>
      </author>
      <author>
         <givenName>F.</givenName>
         <familyName>Bond</familyName>
      </author>
      <author>
         <givenName>S.</givenName>
         <familyName>Fujita</familyName>
      </author>
      <title>The Hinoki sensebank – A Large-scale word sense tagged corpus of Japanese</title>
      <conference>
         <name>Workshop on Frontiers in Linguistically Annotated Corpora 2006</name>
      </conference>
      <publication issuance="continuing">
         <title>Proceedings of the Workshop on Frontiers in Linguistically Annotated Corpora
        2006</title>
         <date>2006</date>
      </publication>
      <startingPage>62</startingPage>
      <endingPage>69</endingPage>
   </ConferencePaper>
   <ConferencePaper ID="tanaka2007" issuance="monographic">
      <author>
         <givenName>Takaaki</givenName>
         <familyName>Tanaka</familyName>
      </author>
      <author>
         <givenName>Francis</givenName>
         <familyName>Bond</familyName>
      </author>
      <author>
         <givenName>Timothy</givenName>
         <familyName>Baldwin</familyName>
      </author>
      <author>
         <givenName>Sanae</givenName>
         <familyName>Fujita</familyName>
      </author>
      <author>
         <givenName>Chikara</givenName>
         <familyName>Hashimoto</familyName>
      </author>
      <title>Word sense disambiguation incorporating lexical and structural semantic
      information</title>
      <conference>
         <name>The 2007 Joint Conference on Empirical Methods in Natural Language Processing and
        Computational Natural Language Learning (EMNLP-CoNLL 2007)</name>
      </conference>
      <publication issuance="continuing">
         <title>Proceedings of the 2007 Joint Conference on Empirical Methods in Natural Language
        Processing and Computational Natural Language Learning (EMNLP-CoNLL 2007)</title>
         <date>2007</date>
      </publication>
      <startingPage>477</startingPage>
      <endingPage>485</endingPage>
   </ConferencePaper>
   <Book ID="tannen1994" issuance="monographic">
      <author>
         <givenName>Deborah</givenName>
         <familyName>Tannen</familyName>
      </author>
      <title>Gender and Discourse</title>
      <place>New York</place>
      <publisher>Oxford University Press</publisher>
      <date>1994</date>
   </Book>
   <JournalArticle ID="tao2004" issuance="monographic">
      <author>
         <givenName>Tao</givenName>
         <familyName>Tao</familyName>
      </author>
      <author>
         <givenName>Chen Xiang</givenName>
         <familyName>Zhai</familyName>
      </author>
      <title>A Mixture Clustering Model for Pseudo Feedback in Information Retrieval</title>
      <journal issuance="continuing">
         <title>Classification, Clustering, and Data Mining Applications</title>
         <volume>0</volume>
         <issue>6</issue>
         <date>2004</date>
      </journal>
      <startingPage>541</startingPage>
      <endingPage>551</endingPage>
   </JournalArticle>
   <JournalArticle ID="tarrantyyy_edi" issuance="monographic">
      <author>
         <givenName>R.J.</givenName>
         <familyName>Tarrant</familyName>
      </author>
      <title>The Editing of Classical Latin Literature</title>
      <journal issuance="continuing">
         <title>Scholarly Editing</title>
         <volume>118</volume>
      </journal>
      <note>Incomplete</note>
   </JournalArticle>
   <ConferencePaper ID="tateishi2004" issuance="monographic">
      <author>
         <givenName>Y.</givenName>
         <familyName>Tateishi</familyName>
      </author>
      <author>
         <givenName>T.</givenName>
         <familyName>Ohta</familyName>
      </author>
      <author>
         <givenName>J.</givenName>
         <familyName>Tsujii</familyName>
      </author>
      <title>Annotation of Predicate-Argument Structure on Molecular Biology Text</title>
      <conference>
         <name>Workshop on Beyond Shallow Analyses IJCNLP-04</name>
      </conference>
      <publication issuance="continuing">
         <title>Proceedings of the Workshop on Beyond Shallow Analyses IJCNLP-04</title>
         <date>2004</date>
      </publication>
   </ConferencePaper>
   <JournalArticle ID="tatman1990" issuance="monographic">
      <author>
         <givenName>J.A.</givenName>
         <familyName>Tatman</familyName>
      </author>
      <author>
         <givenName>R.D.</givenName>
         <familyName>Schachter</familyName>
      </author>
      <title>Dynamic programming and influence diagrams</title>
      <journal issuance="continuing">
         <title>EEE transactions on Systems, Man and Cybernetics</title>
         <volume>20</volume>
         <issue>2</issue>
         <date>1990</date>
      </journal>
      <startingPage>365</startingPage>
      <endingPage>379</endingPage>
   </JournalArticle>
   <ConferencePaper ID="tatu2005" issuance="monographic">
      <author>
         <givenName>Marta</givenName>
         <familyName>Tatu</familyName>
      </author>
      <author>
         <givenName>Dan</givenName>
         <familyName>Moldovan</familyName>
      </author>
      <title>A semantic approach to recognizing textual entailment</title>
      <conference>
         <name>HLT 2005 Conference on Human Language Technology and Empirical Methods in Natural
        Language Processing</name>
      </conference>
      <publication issuance="continuing">
         <title>HLT 05: Proceedings of the Conference on Human Language Technology and Empirical
        Methods in Natural Language Processing</title>
         <date>2005</date>
      </publication>
   </ConferencePaper>
   <ConferencePaper ID="tauson2004" issuance="monographic">
      <author>
         <givenName>O.</givenName>
         <familyName>Tauson</familyName>
      </author>
      <author>
         <givenName>L.</givenName>
         <familyName>Chen</familyName>
      </author>
      <etal/>
      <title>Biological Nomenclatures: A Source of Lexical Knowledge and Ambiguities</title>
      <conference/>
      <publication issuance="continuing">
         <title>Proceedings of PSB</title>
         <date>2004</date>
      </publication>
   </ConferencePaper>
   <Book ID="taylor1989" issuance="monographic">
      <author>
         <givenName>John R.</givenName>
         <familyName>Taylor</familyName>
      </author>
      <title>Linguistic categorization: Prototypes in linguistic theory</title>
      <place>Oxford</place>
      <publisher>Oxford University Press</publisher>
      <date>1989</date>
   </Book>
   <JournalArticle ID="taylor2001" issuance="monographic">
      <author>
         <givenName>P.</givenName>
         <familyName>Taylor</familyName>
      </author>
      <author>
         <givenName>A.</givenName>
         <familyName>Black</familyName>
      </author>
      <author>
         <givenName>R.</givenName>
         <familyName>Caley</familyName>
      </author>
      <title>Heterogeneous relation graphs as a formalism for representing linguistic
      information</title>
      <journal issuance="continuing">
         <title>Speech Communication</title>
         <volume>33</volume>
         <issue>1-2</issue>
         <date>2001</date>
      </journal>
      <startingPage>153</startingPage>
      <endingPage>174</endingPage>
   </JournalArticle>
   <JournalArticle ID="tchizmarova2005" issuance="monographic">
      <author>
         <givenName>Ivelina K.</givenName>
         <familyName>Tchizmarova</familyName>
      </author>
      <title>Hedging functions of the Bulgarian discourse marker xajde</title>
      <journal issuance="continuing">
         <title>Journal of Pragmatics</title>
         <volume>37</volume>
         <issue>8</issue>
         <date>2005</date>
      </journal>
      <startingPage>1143</startingPage>
      <endingPage>1163</endingPage>
   </JournalArticle>
   <BookSection ID="tedlock2000">
      <author>
         <givenName>Dennis</givenName>
         <familyName>Tedlock</familyName>
      </author>
      <title>Towards a Poetics of Polyphony and Translatability</title>
      <book issuance="monographic">
         <editor>
            <givenName>Jerome</givenName>
            <familyName>Rothenberg</familyName>
         </editor>
         <editor>
            <givenName>Steven</givenName>
            <familyName>Clay</familyName>
         </editor>
         <title>A Book of the Book</title>
         <place>New York</place>
         <publisher>Granary Books</publisher>
         <date>2000</date>
      </book>
   </BookSection>
   <ConferencePaper ID="tedyyy_aut" issuance="monographic">
      <author>
         <givenName>Briscoe</givenName>
         <familyName>Ted</familyName>
      </author>
      <author>
         <givenName>John</givenName>
         <familyName>Carroll</familyName>
      </author>
      <title>Automatic extraction of subcategorization from Corpora</title>
      <conference>
         <name>5th Conference on Applied Natural Language Processing</name>
      </conference>
      <publication issuance="continuing">
         <title>Proceedings of the 5th ACL Conference on Applied Natural Conference Processing</title>
      </publication>
      <startingPage>356</startingPage>
      <endingPage>363</endingPage>
   </ConferencePaper>
   <WebSite ID="tei2004" issuance="continuing">
      <author>
         <givenName>C.M.</givenName>
         <familyName>TEI</familyName>
      </author>
      <author>
         <givenName>L.</givenName>
         <familyName>Burnard</familyName>
      </author>
      <title>TEI P4: Guidelines for Electronic Text Encoding and Interchange, XML-compatible
      edition</title>
      <publisher>TEI Consortium</publisher>
      <date>2004</date>
      <url>http://www.tei-c.org/P4X/</url>
   </WebSite>
   <JournalArticle ID="tekalp2000" issuance="monographic">
      <author>
         <givenName>A. Murat</givenName>
         <familyName>Tekalp</familyName>
      </author>
      <author>
         <givenName>Jorn</givenName>
         <familyName>Ostermann</familyName>
      </author>
      <title>Face and 2-D Mesh animation in MPEG-4</title>
      <journal issuance="continuing">
         <title>Signal Processing: Image Communication</title>
         <volume>15</volume>
         <issue>4</issue>
         <date>2000</date>
      </journal>
      <startingPage>387</startingPage>
      <endingPage>421</endingPage>
   </JournalArticle>
   <JournalArticle ID="tenopir2004" issuance="monographic">
      <author>
         <givenName>Carol</givenName>
         <familyName>Tenopir</familyName>
      </author>
      <title>Is Google the Competition?</title>
      <journal issuance="continuing">
         <title>Library Journal</title>
         <volume>129</volume>
         <issue>6</issue>
         <date>1 April 2004</date>
      </journal>
      <startingPage>30</startingPage>
   </JournalArticle>
   <JournalArticle ID="terras2006" issuance="monographic">
      <author>
         <givenName>Melissa</givenName>
         <familyName>Terras</familyName>
      </author>
      <title>Disciplined: Using Educational Studies to Analyse 'Humanities Computing'</title>
      <journal issuance="continuing">
         <title>Literary and Linguistic Computing</title>
         <volume>21</volume>
         <issue>2</issue>
         <date>2006</date>
      </journal>
   </JournalArticle>
   <JournalArticle ID="terras2007" issuance="monographic">
      <author>
         <givenName>Melissa</givenName>
         <familyName>Terras</familyName>
      </author>
      <title>DHQ in the Public Eye</title>
      <journal issuance="continuing">
         <title>Digital Humanities Quarterly</title>
         <volume>1</volume>
         <issue>2</issue>
         <date>2007</date>
      </journal>
   </JournalArticle>
   <JournalArticle ID="terras2009" issuance="monographic">
      <author>
         <givenName>Melissa M.</givenName>
         <familyName>Terras</familyName>
      </author>
      <title>The Potential and Problems in using High Performance Computing in the Arts and
      Humanities: The Researching e-Science Analysis of Census Holding (ReACH) Project</title>
      <journal issuance="continuing">
         <title>Digital Humanities Quarterly</title>
         <volume>3</volume>
         <issue>4</issue>
         <date>2009</date>
      </journal>
   </JournalArticle>
   <Book ID="thacker2004" issuance="monographic">
      <author>
         <givenName>Eugene</givenName>
         <familyName>Thacker</familyName>
      </author>
      <title>Biomedia</title>
      <place>Minneapolis</place>
      <publisher>University of Minnesota Press</publisher>
      <date>2004</date>
   </Book>
   <JournalArticle ID="thaler2008a" issuance="monographic">
      <author>
         <givenName>Richard</givenName>
         <familyName>Thaler</familyName>
      </author>
      <author>
         <givenName>Cass</givenName>
         <familyName>Sunstein</familyName>
      </author>
      <title>Easy Does It: How To Make Lazy People Do the Right Thing</title>
      <journal issuance="continuing">
         <title>The New Republic</title>
         <date>April 9 2008</date>
      </journal>
      <startingPage>20</startingPage>
      <endingPage>24</endingPage>
   </JournalArticle>
   <Book ID="thaler2008b" issuance="monographic">
      <author>
         <givenName>Richard</givenName>
         <familyName>Thaler</familyName>
      </author>
      <author>
         <givenName>Cass</givenName>
         <familyName>Sunstein</familyName>
      </author>
      <title>Nudge: Improving Decisions About Health, Wealth, and Happiness</title>
      <place>New Haven</place>
      <publisher>Yale University Press</publisher>
      <date>2008</date>
   </Book>
   <JournalArticle ID="thaller1991" issuance="monographic">
      <author>
         <givenName>Manfred</givenName>
         <familyName>Thaller</familyName>
      </author>
      <title>The Historical Workstation Project</title>
      <journal issuance="continuing">
         <title>Computers and the Humanities</title>
         <volume>25</volume>
         <date>1991</date>
      </journal>
      <startingPage>149</startingPage>
      <endingPage>162</endingPage>
   </JournalArticle>
   <JournalArticle ID="thaller2004" issuance="monographic">
      <author>
         <givenName>Manfred</givenName>
         <familyName>Thaller</familyName>
      </author>
      <title>Digital Manuscripts as Base Line for Dynamic Editions</title>
      <journal issuance="continuing">
         <title>Linguistica Computazionale</title>
         <volume>20-21</volume>
         <date>2004</date>
      </journal>
      <startingPage>489</startingPage>
      <endingPage>511</endingPage>
   </JournalArticle>
   <JournalArticle ID="thelwall2005" issuance="monographic">
      <author>
         <givenName>Mike</givenName>
         <familyName>Thelwall</familyName>
      </author>
      <title>Creating and using Web corpora</title>
      <journal issuance="continuing">
         <title>International Journal of Corpus Linguistics</title>
         <volume>10</volume>
         <issue>4</issue>
         <date>2005</date>
      </journal>
      <startingPage>517</startingPage>
      <endingPage>541</endingPage>
   </JournalArticle>
   <JournalArticle ID="thierstein2009" issuance="monographic">
      <author>
         <givenName>J.</givenName>
         <familyName>Thierstein</familyName>
      </author>
      <title>Education in the Digital Age</title>
      <journal issuance="continuing">
         <title>EDUCAUSE Review</title>
         <volume>44</volume>
         <issue>1</issue>
         <date>2009</date>
      </journal>
      <startingPage>33</startingPage>
      <endingPage>34</endingPage>
   </JournalArticle>
   <Book ID="thomas1981" issuance="monographic">
      <author>
         <givenName>F.</givenName>
         <familyName>Thomas</familyName>
      </author>
      <author>
         <givenName>O.</givenName>
         <familyName>Johnston</familyName>
      </author>
      <title>Disney animation, the illusion of life</title>
      <place>New York</place>
      <publisher>Abbeville Press</publisher>
      <date>1981</date>
   </Book>
   <WebSite ID="thomas1999" issuance="continuing">
      <author>
         <givenName>William G.</givenName>
         <familyName>Thomas</familyName>
      </author>
      <title>Remarks at the Presidential Sites and Libraries Conference at the George Bush
      Presidential Library, College Station, Texas</title>
      <publisher>Virginia Center for Digital History</publisher>
      <date>1999</date>
      <url>http://www2.vcdh.virginia.edu/presidential.html</url>
   </WebSite>
   <JournalArticle ID="thomas2007a" issuance="monographic">
      <author>
         <givenName>Julia</givenName>
         <familyName>Thomas</familyName>
      </author>
      <title>Getting the Picture: Word and Image in the Digital Archive</title>
      <journal issuance="continuing">
         <title>European Journal of English Studies</title>
         <volume>11</volume>
         <issue>2</issue>
         <date>August 2007</date>
      </journal>
      <startingPage>193</startingPage>
      <endingPage>206</endingPage>
   </JournalArticle>
   <Book ID="thomas2007b" issuance="monographic">
      <author>
         <givenName>Susan</givenName>
         <familyName>Thomas</familyName>
      </author>
      <title>Paradigm Workbook on Digital Private Papers</title>
      <place>Oxford</place>
      <publisher>Bodleian Library</publisher>
      <date>2007</date>
   </Book>
   <JournalArticle ID="thomas2008" issuance="monographic">
      <author>
         <givenName>E.</givenName>
         <familyName>Thomas</familyName>
      </author>
      <author>
         <givenName>D.</givenName>
         <familyName>Gillespie</familyName>
      </author>
      <title>Weaving Together Undergraduate Research, Mentoring of Junior Faculty, and Assessment: The
      Case of an Interdisciplinary Program</title>
      <journal issuance="continuing">
         <title>Innovative Higher Education</title>
         <volume>33</volume>
         <issue>1</issue>
         <date>1 June 2008</date>
      </journal>
      <startingPage>29</startingPage>
      <endingPage>38</endingPage>
   </JournalArticle>
   <BookSection ID="thorisson2002">
      <author>
         <givenName>K.R.</givenName>
         <familyName>Thórisson</familyName>
      </author>
      <title>Natural turn-taking needs no manual: Computational theory and model, from perception to
      action</title>
      <book issuance="monographic">
         <editor>
            <givenName>G.</givenName>
            <familyName>Granström</familyName>
         </editor>
         <title>Multimodality in language speech systems</title>
         <place>Dordrecht</place>
         <publisher>Kluwer Academic</publisher>
         <date>2002</date>
      </book>
      <startingPage>173</startingPage>
      <endingPage>207</endingPage>
   </BookSection>
   <ConferencePaper ID="thurmair1990" issuance="monographic">
      <author>
         <givenName>G.</givenName>
         <familyName>Thurmair</familyName>
      </author>
      <title>METAL: Computer Integrated Translation</title>
      <conference>
         <name>Workshop on Machine Translation</name>
      </conference>
      <publication issuance="continuing">
         <title>Proceedings of the Workshop on Machine Translation</title>
         <date>1990</date>
      </publication>
   </ConferencePaper>
   <ConferencePaper ID="thurmair2003" issuance="monographic">
      <author>
         <givenName>G.</givenName>
         <familyName>Thurmair</familyName>
      </author>
      <title>Making Term Extraction Tools Usable.</title>
      <conference>
         <name>EAMT-CLAW</name>
      </conference>
      <publication issuance="continuing">
         <title>Proceedings of EAMT-CLAW</title>
         <date>2003</date>
      </publication>
   </ConferencePaper>
   <JournalArticle ID="tibbo2003" issuance="monographic">
      <author>
         <givenName>H.R.</givenName>
         <familyName>Tibbo</familyName>
      </author>
      <title>Primarily History in America: How U.S. Historians Search for Primary Materials at the
      Dawn of the Digital Age</title>
      <journal issuance="continuing">
         <title>The American Archivist</title>
         <volume>66</volume>
         <date>2003</date>
      </journal>
      <startingPage>9</startingPage>
      <endingPage>50</endingPage>
   </JournalArticle>
   <WebSite ID="tilkov2007" issuance="continuing">
      <author>
         <givenName>S.</givenName>
         <familyName>Tilkov</familyName>
      </author>
      <title>A Brief Introduction to REST</title>
      <publisher>infoQ</publisher>
      <date>December 2007</date>
      <url>http://www.infoq.com/articles/rest-introduction</url>
   </WebSite>
   <BookSection ID="tillot1972">
      <author>
         <givenName>P.M.</givenName>
         <familyName>Tillot</familyName>
      </author>
      <title>Sources of Inaccuracy in the 1851 and 1861 Censuses</title>
      <book issuance="monographic">
         <author>
            <givenName>E.A.</givenName>
            <familyName>Wrigley</familyName>
         </author>
         <title>Nineteenth-Century Society: Essays in the Use of Quantitative Methods for the Study of
        Social Data</title>
         <place>Cambridge</place>
         <publisher>Cambridge University Press</publisher>
         <date>1972</date>
      </book>
      <startingPage>82</startingPage>
      <endingPage>133</endingPage>
   </BookSection>
   <JournalArticle ID="tmkoczy2006" issuance="monographic">
      <author>
         <givenName>Jernej</givenName>
         <familyName>Tmkoczy</familyName>
      </author>
      <author>
         <givenName>Ziga</givenName>
         <familyName>Turk</familyName>
      </author>
      <author>
         <givenName>Vlado</givenName>
         <familyName>Stankovski</familyName>
      </author>
      <title>A Grid-Based Architecture for Personalized Federation of Digital Libraries</title>
      <journal issuance="continuing">
         <title>Library Collections, Acquisitions, and Technical Services</title>
         <volume>30</volume>
         <issue>3-4</issue>
         <date>2006</date>
      </journal>
      <startingPage>139</startingPage>
      <endingPage>153</endingPage>
   </JournalArticle>
   <Book ID="toates2001" issuance="monographic">
      <author>
         <givenName>F.</givenName>
         <familyName>Toates</familyName>
      </author>
      <title>Biological Psychology An Integrative Approach</title>
      <publisher>Prentice Hall</publisher>
      <date>2001</date>
   </Book>
   <Book ID="tognini2001" issuance="monographic">
      <author>
         <givenName>E.</givenName>
         <familyName>Tognini-Bonelli</familyName>
      </author>
      <title>Corpus linguistics at work</title>
      <place>Amsterdam</place>
      <publisher>Benjamins</publisher>
      <date>2001</date>
   </Book>
   <ConferencePaper ID="tokunaga2006" issuance="monographic">
      <author>
         <givenName>T.</givenName>
         <familyName>Tokunaga</familyName>
      </author>
      <etal/>
      <title>Infrastructure for standardization of asian languages resources</title>
      <conference>
         <name>COLING/ACL 2006</name>
      </conference>
      <publication issuance="continuing">
         <title>Proceedings of the COLING/ACL 2006</title>
         <date>2006</date>
      </publication>
      <startingPage>827</startingPage>
      <endingPage>834</endingPage>
   </ConferencePaper>
   <JournalArticle ID="tokunaga2008" issuance="monographic">
      <author>
         <givenName>Takenobu</givenName>
         <familyName>Tokunaga</familyName>
      </author>
      <author>
         <givenName>Chu-Ren</givenName>
         <familyName>Huang</familyName>
      </author>
      <author>
         <givenName>Sophia Yat Mei</givenName>
         <familyName>Lee</familyName>
      </author>
      <title>Asian language resources: the state-of-the-art</title>
      <journal issuance="continuing">
         <title>Language Resources and Evaluation</title>
         <volume>42</volume>
         <issue>2</issue>
         <date>2008</date>
      </journal>
      <startingPage>109</startingPage>
      <endingPage>116</endingPage>
   </JournalArticle>
   <JournalArticle ID="tomaszek2008" issuance="monographic">
      <author>
         <givenName>Patricia</givenName>
         <familyName>Tomaszek</familyName>
      </author>
      <title>Conference Review: Reading Digital Literature at Brown University, October 4-7,
      2007.</title>
      <journal issuance="continuing">
         <title>Digital Humanities Quarterly</title>
         <volume>2</volume>
         <issue>1</issue>
         <date>2008</date>
      </journal>
   </JournalArticle>
   <ConferencePaper ID="tong2001" issuance="monographic">
      <author>
         <givenName>R.</givenName>
         <familyName>Tong</familyName>
      </author>
      <title>An Operational System for Detecting and Tracking Opinions in Online Discussions</title>
      <conference>
         <name>SIGIR Workshop on Operational Text Classification</name>
      </conference>
      <publication issuance="continuing">
         <title>Working Notes of the SIGIR Workshop on Operational Text Classification</title>
         <date>2001</date>
      </publication>
      <startingPage>1</startingPage>
      <endingPage>6</endingPage>
   </ConferencePaper>
   <BookSection ID="tosca2003">
      <author>
         <givenName>Susana</givenName>
         <familyName>Tosca</familyName>
      </author>
      <title>The Quest Problem in Computer Games</title>
      <book issuance="monographic">
         <title>Proceedings of the First International Conference on Technologies for Interactive
        Digital Storytelling and Entertainment TIDSE ’03</title>
         <publisher>Fraunhofer IRB Verlag</publisher>
         <date>2003</date>
      </book>
      <note>http://www.it-c.dk/people/tosca/quest.htm</note>
   </BookSection>
   <ConferencePaper ID="toselli2007" issuance="monographic">
      <author>
         <givenName>Alejandro</givenName>
         <familyName>Toselli</familyName>
      </author>
      <author>
         <givenName>Veronica</givenName>
         <familyName>Romero</familyName>
      </author>
      <author>
         <givenName>Enrique</givenName>
         <familyName>Vidal</familyName>
      </author>
      <title>Viterbi Based Alignment Between Text Images and Their Transcripts</title>
      <conference>
         <name>LaTeCH 2007</name>
      </conference>
      <publication issuance="continuing">
         <title>Proceedings of the Workshop on Language Technology for Cultural Heritage Data</title>
         <date>2007</date>
      </publication>
      <startingPage>9</startingPage>
      <endingPage>16</endingPage>
   </ConferencePaper>
   <JournalArticle ID="toton2009" issuance="monographic">
      <author>
         <givenName>Sarah</givenName>
         <familyName>Toton</familyName>
      </author>
      <title>Teaching and Learning from the U.S. South in Global Contexts: A Case Study of Southern
      Spaces and Southcomb</title>
      <journal issuance="continuing">
         <title>Digital Humanities Quarterly</title>
         <volume>3</volume>
         <issue>2</issue>
         <date>2009</date>
      </journal>
   </JournalArticle>
   <ConferencePaper ID="toutanova2002a" issuance="monographic">
      <author>
         <givenName>Kristina</givenName>
         <familyName>Toutanova</familyName>
      </author>
      <author>
         <givenName>Robert C.</givenName>
         <familyName>Moore</familyName>
      </author>
      <title>A note on undetected typing errors</title>
      <conference>
         <name>40th Annual Meeting of the Association for Computational Linguistics</name>
      </conference>
      <publication issuance="continuing">
         <title>Proceedings of the 40th Annual Meeting of the Association for Computational Linguistics
        (ACL 2002)</title>
         <date>2002</date>
      </publication>
   </ConferencePaper>
   <ConferencePaper ID="toutanova2002b" issuance="monographic">
      <author>
         <givenName>Kristina</givenName>
         <familyName>Toutanova</familyName>
      </author>
      <author>
         <givenName>Robert C.</givenName>
         <familyName>Moore</familyName>
      </author>
      <title>Pronunciation Modeling for Improved Spelling Correction</title>
      <conference>
         <name>40th Annual Meeting of the Association for Computational Linguistics</name>
      </conference>
      <publication issuance="continuing">
         <title>Proceedings of the 40th Annual Meeting of the Association for Computational Linguistics
        (ACL 2002)</title>
         <date>2002</date>
      </publication>
      <startingPage>144</startingPage>
      <endingPage>151</endingPage>
   </ConferencePaper>
   <JournalArticle ID="toutanova2005" issuance="monographic">
      <author>
         <givenName>Kristina</givenName>
         <familyName>Toutanova</familyName>
      </author>
      <author>
         <givenName>Christopher D.</givenName>
         <familyName>Manning</familyName>
      </author>
      <author>
         <givenName>Dan</givenName>
         <familyName>Flickinger</familyName>
      </author>
      <author>
         <givenName>Stephan</givenName>
         <familyName>Oepen</familyName>
      </author>
      <title>Stochastic HPSG Parse disambiguation using the Redwoods corpus</title>
      <journal issuance="continuing">
         <title>Research on Language and Computation</title>
         <volume>3</volume>
         <issue>1</issue>
         <date>2005</date>
      </journal>
      <startingPage>83</startingPage>
      <endingPage>105</endingPage>
   </JournalArticle>
   <JournalArticle ID="traum1992" issuance="monographic">
      <author>
         <givenName>D.R.</givenName>
         <familyName>Traum</familyName>
      </author>
      <author>
         <givenName>E.A.</givenName>
         <familyName>Hinkelman</familyName>
      </author>
      <title>Conversation acts in task-oriented spoken dialogue</title>
      <journal issuance="continuing">
         <title>Computational Intelligence</title>
         <volume>8</volume>
         <issue>3</issue>
         <date>1992</date>
      </journal>
      <startingPage>575</startingPage>
      <endingPage>599</endingPage>
   </JournalArticle>
   <JournalArticle ID="traum2000_20q" issuance="monographic">
      <author>
         <givenName>D.R.</givenName>
         <familyName>Traum</familyName>
      </author>
      <title>20 Questions for dialogue act taxonomies</title>
      <journal issuance="continuing">
         <title>Journal of Semantics</title>
         <volume>17</volume>
         <issue>1</issue>
         <date>2000</date>
      </journal>
      <startingPage>7</startingPage>
      <endingPage>30</endingPage>
   </JournalArticle>
   <BookSection ID="traum2004">
      <author>
         <givenName>D.</givenName>
         <familyName>Traum</familyName>
      </author>
      <title>Issues in multi-party dialogues</title>
      <book issuance="monographic">
         <editor>
            <givenName>F.</givenName>
            <familyName>Dignum</familyName>
         </editor>
         <title>Advances in agent communication</title>
         <publisher>Springer-Verlag LNCS</publisher>
         <date>2004</date>
      </book>
      <startingPage>201</startingPage>
      <endingPage>211</endingPage>
   </BookSection>
   <JournalArticle ID="trillin1998" issuance="monographic">
      <author>
         <givenName>C.</givenName>
         <familyName>Trillin</familyName>
      </author>
      <title>The Trouble with Transcripts</title>
      <journal issuance="continuing">
         <title>Time</title>
         <volume>151</volume>
         <issue>19</issue>
         <date>18 May 1998</date>
      </journal>
      <startingPage>34</startingPage>
   </JournalArticle>
   <JournalArticle ID="trimbur1989" issuance="monographic">
      <author>
         <givenName>John</givenName>
         <familyName>Trimbur</familyName>
      </author>
      <title>Consensus and Difference in Collaborative Learning</title>
      <journal issuance="continuing">
         <title>College English</title>
         <volume>51</volume>
         <issue>6</issue>
         <date>1989</date>
      </journal>
      <startingPage>602</startingPage>
      <endingPage>616</endingPage>
   </JournalArticle>
   <Book ID="trippel2006" issuance="monographic">
      <author>
         <givenName>T.</givenName>
         <familyName>Trippel</familyName>
      </author>
      <title>The lexicon graph model: A generic model for multimodal lexicon development</title>
      <place>Saarbrücken, Germany</place>
      <publisher>AQ-Verlag</publisher>
      <date>2006</date>
   </Book>
   <ConferencePaper ID="tronstad2001" issuance="monographic">
      <author>
         <givenName>Ragnhild</givenName>
         <familyName>Tronstad</familyName>
      </author>
      <title>Semiotic and Nonsemiotic MUD Performance</title>
      <additionalTitle>http://www.cosignconference.org/cosign2001/papers/Tronstad.pdf</additionalTitle>
      <conference>
         <name>COSIGN</name>
      </conference>
      <publication issuance="continuing">
         <title>Computational Semiotics for Games and New Media</title>
         <date>2001</date>
      </publication>
   </ConferencePaper>
   <ConferencePaper ID="tsarkov2006" issuance="monographic">
      <author>
         <givenName>D.</givenName>
         <familyName>Tsarkov</familyName>
      </author>
      <author>
         <givenName>I.</givenName>
         <familyName>Horrocks</familyName>
      </author>
      <title>FaCT++ Description Logic Reasoner: System Description</title>
      <conference>
         <name>IJCAR 2006</name>
      </conference>
      <publication issuance="continuing">
         <title>Proceedings of the International Joint Conference on Automated Reasoning</title>
         <date>2006</date>
      </publication>
      <startingPage>292</startingPage>
      <endingPage>297</endingPage>
   </ConferencePaper>
   <ConferencePaper ID="tsuchiya2005" issuance="monographic">
      <author>
         <givenName>Masatoshi</givenName>
         <familyName>Tsuchiya</familyName>
      </author>
      <author>
         <givenName>Takehito</givenName>
         <familyName>Utsuro</familyName>
      </author>
      <author>
         <givenName>Suguru</givenName>
         <familyName>Matsuyoshi</familyName>
      </author>
      <author>
         <givenName>Satoshi</givenName>
         <familyName>Sato</familyName>
      </author>
      <author>
         <givenName>Seiichi</givenName>
         <familyName>Nakagawa</familyName>
      </author>
      <title>A corpus for classifying usages of Japanese compound functional expressions</title>
      <conference>
         <name>10th Conference of the Pacific Association for Computational Linguistics</name>
      </conference>
      <publication issuance="continuing">
         <title>Proceedings of the 10th Conference of the Pacific Association for Computational
        Linguistics</title>
         <date>2005</date>
      </publication>
   </ConferencePaper>
   <JournalArticle ID="tsuchiya2006" issuance="monographic">
      <author>
         <givenName>Masatoshi</givenName>
         <familyName>Tsuchiya</familyName>
      </author>
      <author>
         <givenName>Takehito</givenName>
         <familyName>Utsuro</familyName>
      </author>
      <author>
         <givenName>Suguru</givenName>
         <familyName>Matsuyoshi</familyName>
      </author>
      <author>
         <givenName>Satoshi</givenName>
         <familyName>Sato</familyName>
      </author>
      <author>
         <givenName>Seiichi</givenName>
         <familyName>Nakagawa</familyName>
      </author>
      <title>Development and Analysis of An Example Database of Japanese Compound Functional
      Expressions</title>
      <journal issuance="continuing">
         <title>Transactions of Information Processing Society of Japan</title>
         <volume>47</volume>
         <issue>6</issue>
         <date>2006</date>
      </journal>
      <startingPage>497</startingPage>
      <endingPage>512</endingPage>
   </JournalArticle>
   <ConferencePaper ID="tsurumaru1986" issuance="monographic">
      <author>
         <givenName>Hiroaki</givenName>
         <familyName>Tsurumaru</familyName>
      </author>
      <author>
         <givenName>Toru</givenName>
         <familyName>Hitaka</familyName>
      </author>
      <author>
         <givenName>Sho</givenName>
         <familyName>Yoshida</familyName>
      </author>
      <title>An attempt to automatic thesaurus construction from an ordinary Japanese language
      dictionary</title>
      <conference>
         <name>COLING 1986: 11th International Coference on Computational linguistics</name>
      </conference>
      <publication issuance="continuing">
         <title>Proceedings of the 11th International Coference on Computational linguistics</title>
         <date>1986</date>
      </publication>
      <startingPage>445</startingPage>
      <endingPage>447</endingPage>
   </ConferencePaper>
   <ConferencePaper ID="tsuruoka2003" issuance="monographic">
      <author>
         <givenName>Y.</givenName>
         <familyName>Tsuruoka</familyName>
      </author>
      <author>
         <givenName>J.</givenName>
         <familyName>Tsujii</familyName>
      </author>
      <title>Probabilistic Term Variant Generator for Biomedical Terms</title>
      <conference>
         <name>ACM SIGIR</name>
      </conference>
      <publication issuance="continuing">
         <title>Proceedings of ACM SIGIR</title>
         <date>2003</date>
      </publication>
   </ConferencePaper>
   <Book ID="tuchman1989" issuance="monographic">
      <author>
         <givenName>G.</givenName>
         <familyName>Tuchman</familyName>
      </author>
      <author>
         <givenName>N. E.</givenName>
         <familyName>Fortin</familyName>
      </author>
      <title>Edging Women Out: Victorian Novelists, Publishers, and Social Change</title>
      <place>New Haven</place>
      <publisher>Yale University Press</publisher>
      <date>1989</date>
   </Book>
   <BookSection ID="tuchman2000">
      <author>
         <givenName>G.</givenName>
         <familyName>Tuchman</familyName>
      </author>
      <title>Historical Social Science: Methodologies, Methods, and Meanings</title>
      <book issuance="monographic">
         <author>
            <familyName>Denzin et al</familyName>
         </author>
         <title>Handbook of Qualitative Research</title>
         <place>Thousand Oaks and London</place>
         <publisher>Sage Publications</publisher>
         <date>2000</date>
      </book>
      <startingPage>306</startingPage>
      <endingPage>323</endingPage>
   </BookSection>
   <JournalArticle ID="tucker1995" issuance="monographic">
      <author>
         <givenName>D.M.</givenName>
         <familyName>Tucker</familyName>
      </author>
      <author>
         <givenName>P.</givenName>
         <familyName>Luu</familyName>
      </author>
      <author>
         <givenName>K.H.</givenName>
         <familyName>Pribram</familyName>
      </author>
      <title>Social and Emotional Self-regulation</title>
      <journal issuance="continuing">
         <title>Annals of the New York Academy of Sciences</title>
         <issue>769</issue>
         <date>1995</date>
      </journal>
      <startingPage>213</startingPage>
      <endingPage>239</endingPage>
   </JournalArticle>
   <ConferencePaper ID="tufis1998" issuance="monographic">
      <author>
         <givenName>D.</givenName>
         <familyName>Tufis</familyName>
      </author>
      <author>
         <givenName>N.</givenName>
         <familyName>Ide</familyName>
      </author>
      <author>
         <givenName>T.</givenName>
         <familyName>Erjavec</familyName>
      </author>
      <title>Standardized Specifications, Development and Assessment of Large Morpho-Lexical Resources
      for Six Central and Eastern European Languages</title>
      <conference>
         <name>LREC '1998</name>
      </conference>
      <publication issuance="continuing">
         <title>Proceedings LREC '1998</title>
         <date>1998</date>
      </publication>
      <startingPage>233</startingPage>
      <endingPage>249</endingPage>
   </ConferencePaper>
   <ConferencePaper ID="tufis2000" issuance="monographic">
      <author>
         <givenName>D.</givenName>
         <familyName>Tufis</familyName>
      </author>
      <title>Using a Large Set of Eagles-compliant Morpho-Syntactic Descriptors as a Tagset for
      Probabilistic Tagging</title>
      <conference>
         <name>LREC 2000</name>
      </conference>
      <publication issuance="continuing">
         <title>Proceedings LREC '2000</title>
         <date>2000</date>
      </publication>
      <startingPage>1105</startingPage>
      <endingPage>1112</endingPage>
   </ConferencePaper>
   <ConferencePaper ID="tufis2002a" issuance="monographic">
      <author>
         <givenName>D.</givenName>
         <familyName>Tufis</familyName>
      </author>
      <title>A Cheap and Fast Way to Build Useful Translation Lexicons</title>
      <conference>
         <name>19th International Conference on Computational Linguistic</name>
      </conference>
      <publication issuance="continuing">
         <title>Proceedings of the 19th International Conference on Computational Linguistics,
        COLING2002</title>
         <date>2002</date>
      </publication>
      <startingPage>1030</startingPage>
      <endingPage>1036</endingPage>
   </ConferencePaper>
   <JournalArticle ID="tufis2002b" issuance="monographic">
      <author>
         <givenName>D.</givenName>
         <familyName>Tufis</familyName>
      </author>
      <author>
         <givenName>A. M.</givenName>
         <familyName>Barbu</familyName>
      </author>
      <title>Revealing Translators Knowledge: Statistical Methods in Constructing Practical
      Translation Lexicons for Language and Speech Processing</title>
      <journal issuance="continuing">
         <title>International Journal of Speech Technology</title>
         <issue>5</issue>
         <date>2002</date>
      </journal>
      <startingPage>199</startingPage>
      <endingPage>209</endingPage>
   </JournalArticle>
   <ConferencePaper ID="tufis2003" issuance="monographic">
      <author>
         <givenName>D.</givenName>
         <familyName>Tufis</familyName>
      </author>
      <author>
         <givenName>A. M.</givenName>
         <familyName>Barbu</familyName>
      </author>
      <author>
         <givenName>R.</givenName>
         <familyName>Ion</familyName>
      </author>
      <title>TREQ-AL: A Word Alignment System with Limited Language Resources</title>
      <conference>
         <name>HLT-NAACL 2003 Workshop on Building and Using Parallel Texts: Data Driven Machine
        Translation and Beyond</name>
      </conference>
      <publication issuance="continuing">
         <title>roceedings of the HLT-NAACL 2003 Workshop on Building and Using Parallel Texts: Data
        Driven Machine Translation and Beyond</title>
         <date>2003</date>
      </publication>
      <startingPage>36</startingPage>
      <endingPage>39</endingPage>
   </ConferencePaper>
   <ConferencePaper ID="tufis2004" issuance="monographic">
      <author>
         <givenName>Dan</givenName>
         <familyName>Tufis</familyName>
      </author>
      <author>
         <givenName>Radu</givenName>
         <familyName>Ion</familyName>
      </author>
      <author>
         <givenName>Nancy</givenName>
         <familyName>Ide</familyName>
      </author>
      <title>Fine-Grained Word Sense Disambiguation Based on Parallel Corpora, Word Alignment, Word
      Clustering and Aligned Wordnets</title>
      <conference>
         <name>COLING 2004</name>
      </conference>
      <publication issuance="continuing">
         <title>Proceedings of the Twentieth International Conference on Computational
        Linguistics</title>
         <date>2004</date>
      </publication>
   </ConferencePaper>
   <BookSection ID="tufisyyy_cor">
      <author>
         <givenName>D.</givenName>
         <familyName>Tufis</familyName>
      </author>
      <author>
         <givenName>M.</givenName>
         <familyName>Barbu</familyName>
      </author>
      <author>
         <givenName>V.</givenName>
         <familyName>Patrascu</familyName>
      </author>
      <author>
         <givenName>G.</givenName>
         <familyName>Rotariu</familyName>
      </author>
      <author>
         <givenName>C.</givenName>
         <familyName>Popescu</familyName>
      </author>
      <title>Corpora and Corpus-Based Morpho-Lexical Processing</title>
      <book issuance="monographic">
         <editor>
            <givenName>D.</givenName>
            <familyName>Tufis</familyName>
         </editor>
         <editor>
            <givenName>P.</givenName>
            <familyName>Anderson</familyName>
         </editor>
         <title>Recent Advances in Romanian Language Technology</title>
         <publisher>Editura Academiei</publisher>
      </book>
      <startingPage>35</startingPage>
      <endingPage>56</endingPage>
   </BookSection>
   <Book ID="tufte1998" issuance="monographic">
      <author>
         <givenName>Edward Rolf</givenName>
         <familyName>Tufte</familyName>
      </author>
      <title>Visual Explanations: Images and Quantities, Evidence and Narrative</title>
      <place>Cheshire, CT</place>
      <publisher>Graphics Press</publisher>
      <date>1998</date>
   </Book>
   <JournalArticle ID="tukey1949" issuance="monographic">
      <author>
         <givenName>J. w.</givenName>
         <familyName>Tukey</familyName>
      </author>
      <title>Comparing Individual Means in the Analysis of Variance.</title>
      <journal issuance="continuing">
         <title>Biometrics</title>
         <volume>5</volume>
         <date>1949</date>
      </journal>
      <startingPage>99</startingPage>
      <endingPage>114</endingPage>
   </JournalArticle>
   <JournalArticle ID="turing1950" issuance="monographic">
      <author>
         <givenName>Alan</givenName>
         <familyName>Turing</familyName>
      </author>
      <title>Computing Machinery and Intelligence</title>
      <journal issuance="continuing">
         <title>Mind</title>
         <volume>59</volume>
         <issue>236</issue>
         <date>1950</date>
      </journal>
      <startingPage>433</startingPage>
      <endingPage>460</endingPage>
   </JournalArticle>
   <Book ID="turkle1995" issuance="monographic">
      <author>
         <givenName>S.</givenName>
         <familyName>Turkle</familyName>
      </author>
      <title>Life on the Screen: Identity in the Age of the Internet</title>
      <place>New York</place>
      <publisher>Simon and Schuster</publisher>
      <date>1995</date>
   </Book>
   <BookSection ID="turkle2005">
      <author>
         <givenName>Sherry</givenName>
         <familyName>Turkle</familyName>
      </author>
      <title>Computer Games as Evocative Objects: From Projective Screens to Relational
      Artifacts</title>
      <book issuance="monographic">
         <editor>
            <givenName>Joost</givenName>
            <familyName>Raessens</familyName>
         </editor>
         <editor>
            <givenName>Jeffrey</givenName>
            <familyName>Goldstein</familyName>
         </editor>
         <title>Handbook of Computer Game Studies</title>
         <place>Cambridge, MA</place>
         <publisher>MIT Press</publisher>
         <date>2005</date>
      </book>
   </BookSection>
   <JournalArticle ID="turner2005" issuance="monographic">
      <author>
         <givenName>Fred</givenName>
         <familyName>Turner</familyName>
      </author>
      <author/>
      <author/>
      <author/>
      <title>Where the Counterculture Met The New Economy: The WELL and the Origins of Virtual
      Community</title>
      <journal issuance="continuing">
         <title>Technology and Culture</title>
         <volume>46</volume>
         <issue>3</issue>
         <date>2005</date>
      </journal>
      <startingPage>485</startingPage>
      <endingPage>512</endingPage>
   </JournalArticle>
   <WebSite ID="turner2006" issuance="continuing">
      <author>
         <givenName>A.</givenName>
         <familyName>Turner</familyName>
      </author>
      <title>Introduction to NeoGeography</title>
      <publisher>O'Reilly media</publisher>
      <date>2006</date>
      <url>http://oreilly.com/catalog/9780596529956/</url>
   </WebSite>
   <ConferencePaper ID="turney2002" issuance="monographic">
      <author>
         <givenName>Peter</givenName>
         <familyName>Turney</familyName>
      </author>
      <title>Thumbs Up or Thumbs Down? Semantic Orientation Applied to Unsupervised Classification of
      Reviews</title>
      <conference>
         <name>40th Annual Meeting of the Association for Computational Linguistics</name>
      </conference>
      <publication issuance="continuing">
         <title>Proceedings of the 40th Annual Meeting of the Association for Computational Linguistics
        (ACL-02)</title>
         <date>2002</date>
      </publication>
      <startingPage>417</startingPage>
      <endingPage>424</endingPage>
   </ConferencePaper>
   <JournalArticle ID="turney2003" issuance="monographic">
      <author>
         <givenName>P.</givenName>
         <familyName>Turney</familyName>
      </author>
      <author>
         <givenName>M.L.</givenName>
         <familyName>Littman</familyName>
      </author>
      <title>Measuring Praise and Criticism: Inference of Semantic Orientation from
      Association</title>
      <journal issuance="continuing">
         <title>ACM Transactions on Information Systems (TOTS)</title>
         <volume>21</volume>
         <date>2003</date>
      </journal>
      <startingPage>315</startingPage>
      <endingPage>346</endingPage>
   </JournalArticle>
   <ConferencePaper ID="turnhout2005" issuance="monographic">
      <author>
         <givenName>K.</givenName>
         <familyName>van Turnhout</familyName>
      </author>
      <title>Identifying the intended addressee in mixed human–human and human–computer interaction
      from non-verbal features</title>
      <conference>
         <name>International Conference on Multimodal Interfaces (ICMI)</name>
      </conference>
      <publication issuance="continuing">
         <title>Proceedings of the International Conference on Multimodal Interfaces</title>
         <date>2005</date>
      </publication>
      <startingPage>175</startingPage>
      <endingPage>182</endingPage>
   </ConferencePaper>
   <JournalArticle ID="tweedie1996" issuance="monographic">
      <author>
         <givenName>F.J.</givenName>
         <familyName>Tweedie</familyName>
      </author>
      <author>
         <givenName>S.</givenName>
         <familyName>Singh</familyName>
      </author>
      <author>
         <givenName>D.I.</givenName>
         <familyName>Holmes</familyName>
      </author>
      <title>Neural Network Applications in Stylometry: The Federalist Paper</title>
      <journal issuance="continuing">
         <title>Computers and the Humanities</title>
         <volume>30</volume>
         <issue>1</issue>
         <date>1996</date>
      </journal>
      <startingPage>1</startingPage>
      <endingPage>10</endingPage>
   </JournalArticle>
   <JournalArticle ID="tweedieyyy_how" issuance="monographic">
      <author>
         <givenName>F.J.</givenName>
         <familyName>Tweedie</familyName>
      </author>
      <author>
         <givenName>R.H.</givenName>
         <familyName>Baayen</familyName>
      </author>
      <title>How variable May a Constant Be? Measures of Lexical Richness in Perspective</title>
      <journal issuance="continuing">
         <title>Computers and the Humanities</title>
         <volume>32</volume>
         <issue>323</issue>
      </journal>
      <startingPage>352</startingPage>
      <endingPage>1998</endingPage>
   </JournalArticle>
</BiblioSet>
