<mods:mods xmlns:mods="http://www.loc.gov/mods/v3" xmlns:saxon="http://saxon.sf.net/" version="3.2"><mods:name xmlns="http://www.loc.gov/mods/v3" type="personal"><mods:role><mods:roleTerm type="text">author</mods:roleTerm></mods:role><mods:namePart type="given">Andrew</mods:namePart><mods:namePart type="family">Blaikie</mods:namePart></mods:name><mods:name xmlns="http://www.loc.gov/mods/v3" type="personal"><mods:namePart type="given">Eilidh</mods:namePart><mods:namePart type="family">Garrett</mods:namePart><mods:role><mods:roleTerm type="text">author</mods:roleTerm></mods:role></mods:name><mods:name xmlns="http://www.loc.gov/mods/v3" type="personal"><mods:namePart type="given">Ros</mods:namePart><mods:namePart type="family">Davies</mods:namePart></mods:name><mods:typeOfResource xmlns="http://www.loc.gov/mods/v3">text</mods:typeOfResource><mods:relatedItem xmlns="http://www.loc.gov/mods/v3" type="host"><mods:name type="personal"><mods:role><mods:roleTerm type="text">editor</mods:roleTerm></mods:role><mods:namePart type="given">Alysa</mods:namePart><mods:namePart type="family">Levene</mods:namePart></mods:name><mods:name type="personal"><mods:namePart type="given">Samantha</mods:namePart><mods:namePart type="family">Williams</mods:namePart><mods:role><mods:roleTerm type="text">editor</mods:roleTerm></mods:role></mods:name><mods:name type="personal"><mods:namePart type="given">Thomas</mods:namePart><mods:namePart type="family">Nutt</mods:namePart><mods:role><mods:roleTerm type="text">editor</mods:roleTerm></mods:role></mods:name><mods:originInfo><mods:issuance>monographic</mods:issuance><mods:place><mods:placeTerm type="text">London</mods:placeTerm></mods:place><mods:publisher>Palgrave Macmillan</mods:publisher><mods:dateIssued>2005</mods:dateIssued></mods:originInfo><mods:titleInfo><mods:title>Illegitimacy in Britain, 1700-1920</mods:title></mods:titleInfo></mods:relatedItem><mods:genre xmlns="http://www.loc.gov/mods/v3" authority="biblio">Book Section</mods:genre><mods:identifier type="biblio">DHQ-3391.xml</mods:identifier><mods:recordInfo><mods:recordChangeDate>2012-08-10</mods:recordChangeDate><mods:recordCreationDate>2012-08-10</mods:recordCreationDate></mods:recordInfo><mods:titleInfo xmlns="http://www.loc.gov/mods/v3"><mods:title>Migration, Living Strategies and Illegitimate Childbearing; A Comparison of Two Scottish Settings: 1871-1881</mods:title></mods:titleInfo></mods:mods>