<mods:mods xmlns:mods="http://www.loc.gov/mods/v3" version="3.2"><mods:typeOfResource>text</mods:typeOfResource><mods:subject><mods:topic>ID of works referenced</mods:topic></mods:subject><mods:relatedItem type="host"><mods:originInfo><mods:issuance>monographic</mods:issuance><mods:place><mods:placeTerm type="text">Pittsburgh</mods:placeTerm></mods:place><mods:publisher>Archives and Museum Informatics</mods:publisher><mods:dateIssued>2006</mods:dateIssued></mods:originInfo><mods:titleInfo><mods:title>Papers Museums and the Web 2006</mods:title></mods:titleInfo></mods:relatedItem><mods:genre authority="biblio">Book Section</mods:genre><mods:identifier type="biblio">DHQ-256.xml</mods:identifier><mods:recordInfo><mods:recordChangeDate>2009-03-03</mods:recordChangeDate><mods:recordCreationDate>2009-03-03</mods:recordCreationDate></mods:recordInfo><mods:titleInfo><mods:title>Steve.museum: An Ongoing Experiment in Social Tagging, Folksonomy, and
                Museums</mods:title></mods:titleInfo><mods:name type="personal"><mods:namePart type="given">Bruce</mods:namePart><mods:namePart type="family">Wyman</mods:namePart></mods:name><mods:name type="personal"><mods:namePart type="given">Susan</mods:namePart><mods:namePart type="family">Chun</mods:namePart></mods:name><mods:name type="personal"><mods:namePart type="given">Rich</mods:namePart><mods:namePart type="family">Cherry</mods:namePart></mods:name><mods:name type="personal"><mods:namePart type="given">Doug</mods:namePart><mods:namePart type="family">Hiwiller</mods:namePart></mods:name><mods:name type="personal"><mods:namePart type="given">Jennifer</mods:namePart><mods:namePart type="family">Trant</mods:namePart></mods:name><mods:note>http://www.archimuse.com/mw2006/papers/wyman/wyman.html</mods:note></mods:mods>