<mods:mods xmlns:mods="http://www.loc.gov/mods/v3" xmlns:saxon="http://saxon.sf.net/" version="3.2"><mods:name type="personal"><mods:role><mods:roleTerm type="text">author</mods:roleTerm></mods:role><mods:namePart type="given">Paul</mods:namePart><mods:namePart type="family">Clough</mods:namePart></mods:name><mods:name type="personal"><mods:namePart type="given">Robert</mods:namePart><mods:namePart type="family">Gaizauskas</mods:namePart><mods:role><mods:roleTerm type="text">author</mods:roleTerm></mods:role></mods:name><mods:name type="personal"><mods:namePart type="given">Scott</mods:namePart><mods:namePart type="family">Scott</mods:namePart><mods:role><mods:roleTerm type="text">author</mods:roleTerm></mods:role></mods:name><mods:name type="personal"><mods:namePart type="given">Yorick</mods:namePart><mods:namePart type="family">Wilks</mods:namePart><mods:role><mods:roleTerm type="text">author</mods:roleTerm></mods:role></mods:name><mods:name type="conference"><mods:role><mods:roleTerm type="text">creator</mods:roleTerm></mods:role><mods:namePart>Association for Computational Linguistics Conference
                (ACL02)</mods:namePart></mods:name><mods:typeOfResource>text</mods:typeOfResource><mods:genre authority="marcgt">conference publication</mods:genre><mods:originInfo><mods:issuance>monographic</mods:issuance></mods:originInfo><mods:relatedItem type="host"><mods:originInfo><mods:issuance>continuing</mods:issuance></mods:originInfo><mods:titleInfo><mods:title>Proceedings of the Association for Computational Linguistics
                    Conference</mods:title></mods:titleInfo><mods:part><mods:date>2002</mods:date></mods:part></mods:relatedItem><mods:genre authority="biblio">Conference Paper</mods:genre><mods:identifier type="biblio">DHQ-693.xml</mods:identifier><mods:recordInfo><mods:recordChangeDate>2011-09-04</mods:recordChangeDate><mods:recordCreationDate>2009-03-03</mods:recordCreationDate></mods:recordInfo><mods:titleInfo><mods:title>MeTeR: Measuring Text Reuse</mods:title></mods:titleInfo></mods:mods>