<mods:mods xmlns:mods="http://www.loc.gov/mods/v3" xmlns:saxon="http://saxon.sf.net/" version="3.2"><mods:name xmlns="http://www.loc.gov/mods/v3" type="personal"><mods:role><mods:roleTerm type="text">author</mods:roleTerm></mods:role><mods:namePart type="given">Noam</mods:namePart><mods:namePart type="family">Amir</mods:namePart></mods:name><mods:name xmlns="http://www.loc.gov/mods/v3" type="personal"><mods:namePart type="given">Samuel</mods:namePart><mods:namePart type="family">Ron</mods:namePart><mods:role><mods:roleTerm type="text">author</mods:roleTerm></mods:role></mods:name><mods:name xmlns="http://www.loc.gov/mods/v3" type="personal"><mods:namePart type="given">Nathaniel</mods:namePart><mods:namePart type="family">Laor</mods:namePart><mods:role><mods:roleTerm type="text">author</mods:roleTerm></mods:role></mods:name><mods:name xmlns="http://www.loc.gov/mods/v3" type="conference"><mods:role><mods:roleTerm type="text">creator</mods:roleTerm></mods:role><mods:namePart>ISCA Tutorial and Research Workshop (ITRW) on Speech and Emotion</mods:namePart></mods:name><mods:typeOfResource xmlns="http://www.loc.gov/mods/v3">text</mods:typeOfResource><mods:genre xmlns="http://www.loc.gov/mods/v3" authority="marcgt">conference publication</mods:genre><mods:originInfo xmlns="http://www.loc.gov/mods/v3"><mods:issuance>monographic</mods:issuance></mods:originInfo><mods:relatedItem xmlns="http://www.loc.gov/mods/v3" type="host"><mods:originInfo><mods:issuance>continuing</mods:issuance></mods:originInfo><mods:part><mods:extent unit="pages"><mods:start>29</mods:start><mods:end>33</mods:end></mods:extent><mods:date>2000</mods:date></mods:part></mods:relatedItem><mods:genre xmlns="http://www.loc.gov/mods/v3" authority="biblio">Conference Paper</mods:genre><mods:identifier type="biblio">DHQ-2155.xml</mods:identifier><mods:recordInfo><mods:recordChangeDate>2011-06-28</mods:recordChangeDate><mods:recordCreationDate>2009-04-29</mods:recordCreationDate></mods:recordInfo><mods:titleInfo xmlns="http://www.loc.gov/mods/v3"><mods:title>Analysis of an emotional speech corpus in Hebrew based on objective criteria</mods:title></mods:titleInfo></mods:mods>